aclvl_permissions/__init__.py
aclvl_permissions/admin.py
aclvl_permissions/apps.py
aclvl_permissions/models.py
aclvl_permissions/permissions.py
aclvl_permissions/management/__init__.py
aclvl_permissions/management/commands/__init__.py
aclvl_permissions/management/commands/aclvl_set_view_keys.py
tests/__init__.py
tests/test_permissions.py
aclvl_permissions-0.3.0.dist-info/LICENSE
aclvl_permissions-0.3.0.dist-info/METADATA
aclvl_permissions-0.3.0.dist-info/WHEEL
aclvl_permissions-0.3.0.dist-info/top_level.txt
aclvl_permissions-0.3.0.dist-info/RECORD
