Metadata-Version: 2.1
Name: aclvl_permissions
Version: 0.3.0
Summary: A custom Django permissions package.
Home-page: https://github.com/shahbazism/aclvl_permissions
Author: Saeid Shahbazi
Author-email: saeidshahbazi@zohomail.com
License: MIT License
Classifier: Environment :: Web Environment
Classifier: Framework :: Django
Classifier: Framework :: Django :: 3.0
Classifier: Intended Audience :: Developers
Classifier: License :: OSI Approved :: MIT License
Classifier: Operating System :: OS Independent
Classifier: Programming Language :: Python
Classifier: Programming Language :: Python :: 3
Classifier: Programming Language :: Python :: 3.7
Classifier: Programming Language :: Python :: 3.8
Classifier: Programming Language :: Python :: 3.9
Classifier: Topic :: Internet :: WWW/HTTP
Classifier: Topic :: Internet :: WWW/HTTP :: Dynamic Content
License-File: LICENSE
Requires-Dist: Django >=3.0
Requires-Dist: djangorestframework >=3.0
